owlidar/__init__.py
owlidar/extract4solana.py
owlidar-0.1.10.dist-info/WHEEL
owlidar-0.1.10.dist-info/entry_points.txt
owlidar-0.1.10.dist-info/METADATA
owlidar-0.1.10.dist-info/RECORD
