Metadata-Version: 2.3
Name: owlidar
Version: 0.1.10
Summary: Add your description here
Author: Bayan2019
Author-email: Bayan2019 <saparbayevabt@gmail.com>
Requires-Dist: pandas>=2.3.1
Requires-Dist: requests>=2.32.4
Requires-Python: >=3.13
